MANIFEST.in
README.rst
setup.py
randomization/__init__.py
randomization/randomization.py
randomization.egg-info/PKG-INFO
randomization.egg-info/SOURCES.txt
randomization.egg-info/dependency_links.txt
randomization.egg-info/top_level.txt