Metadata-Version: 1.0
Name: randomization
Version: 1.0.0
Summary: Functions to randomize subjects in clinical trials.
Home-page: http://github.com/louden/randomization
Author: Christopher Louden
Author-email: chris@loudenanalytics.com
License: MIT
Keywords: randomization random trial
Platform: UNKNOWN
